README.md
setup.py
ppsrx/__init__.py
ppsrx/_configurations_.py
ppsrx/_main_functions_.py
ppsrx/all_address_type.py
ppsrx/all_applications_type.py
ppsrx/all_policy_type.py
ppsrx/cli_loop.py
ppsrx/devices.py
ppsrx/excel_output.py
ppsrx/load_full_set_configurations.py
ppsrx/logger_config.py
ppsrx/main_script.py
ppsrx/match_policy.py
ppsrx/save_excel_def.py
ppsrx.egg-info/PKG-INFO
ppsrx.egg-info/SOURCES.txt
ppsrx.egg-info/dependency_links.txt
ppsrx.egg-info/entry_points.txt
ppsrx.egg-info/requires.txt
ppsrx.egg-info/top_level.txt